chamelboots/__init__.py
chamelboots/__main__.py
chamelboots/cli.py
chamelboots/constants.py
chamelboots/html/__init__.py
chamelboots/html/utils.py
chamelboots/html/elements/__init__.py
chamelboots/html/packages/__init__.py
chamelboots/html/packages/bootstrap/__init__.py
chamelboots/html/scrapeutils/__init__.py
chamelboots/html/scrapeutils/tables.py
chamelboots/imageutils/__init__.py
chamelboots/treeutils/__init__.py
python_chamelboots-0.0.28.dist-info/AUTHORS.rst
python_chamelboots-0.0.28.dist-info/LICENSE
python_chamelboots-0.0.28.dist-info/METADATA
python_chamelboots-0.0.28.dist-info/WHEEL
python_chamelboots-0.0.28.dist-info/entry_points.txt
python_chamelboots-0.0.28.dist-info/top_level.txt
python_chamelboots-0.0.28.dist-info/RECORD
