Metadata-Version: 2.1
Name: python-chamelboots
Version: 0.0.28
Summary: An example package. Generated with cookiecutter-pylibrary.
Home-page: https://github.com/dm-wyncode/python-chamelboots
Author: Don Morehouse
Author-email: dm.wyncode@gmail.com
License: BSD-2-Clause
Project-URL: Documentation, https://python-chamelboots.readthedocs.io/
Project-URL: Changelog, https://python-chamelboots.readthedocs.io/en/latest/changelog.html
Project-URL: Issue Tracker, https://github.com/dm-wyncode/python-chamelboots/issues
Platform: UNKNOWN
Classifier: Development Status :: 1 - Planning
Classifier: Intended Audience :: Developers
Classifier: License :: OSI Approved :: BSD License
Classifier: Operating System :: Unix
Classifier: Operating System :: POSIX
Classifier: Operating System :: Microsoft :: Windows
Classifier: Programming Language :: Python
Classifier: Programming Language :: Python :: 3
Classifier: Programming Language :: Python :: 3.8
Classifier: Topic :: Text Processing
Requires-Python: >=3.8
Requires-Dist: lxml (>=4.4.1)
Requires-Dist: Chameleon (>=3.6.2)
Requires-Dist: Faker
Requires-Dist: bs4
Requires-Dist: Pillow (>=6.2.1)
